xftsim/__init__.py
xftsim/arch.py
xftsim/data.py
xftsim/effect.py
xftsim/filters.py
xftsim/founders.py
xftsim/index.py
xftsim/io.py
xftsim/mate.py
xftsim/ped.py
xftsim/ped2.py
xftsim/proc.py
xftsim/reproduce.py
xftsim/sim.py
xftsim/stats.py
xftsim/struct.py
xftsim/utils.py
xftsim/maps/ceu.hg19.map
xftsim-0.2.0.dist-info/LICENSE
xftsim-0.2.0.dist-info/METADATA
xftsim-0.2.0.dist-info/WHEEL
xftsim-0.2.0.dist-info/top_level.txt
xftsim-0.2.0.dist-info/RECORD
