Metadata-Version: 2.1
Name: xftsim
Version: 0.2.0
Author: Richard Border
Author-email: border.richard@gmail.com
License-File: LICENSE
Requires-Dist: funcy
Requires-Dist: networkx
Requires-Dist: nptyping
Requires-Dist: numba ==0.56.4
Requires-Dist: numpy
Requires-Dist: pandas
Requires-Dist: pandas-plink
Requires-Dist: scipy
Requires-Dist: sgkit
Requires-Dist: xarray
